Workbook

Sheet Instrucciones
A1: LISTA DE CHEQUEO FINAL DEL PROYECTO — SIGTM
A4: Que es este instrumento
A5: Es la verificación que el equipo se hace a sí mismo antes de entregar. No sirve para demostrar que todo está bien: sirve para saber qué falta mientras todavía hay tiempo de arreglarlo.
A7: Como se diligencia
A8: Cada criterio se marca con Si, No, Parcial o N.A. Las celdas de la columna 'Cumple' tienen lista desplegable y se colorean solas. Un criterio marcado No o Parcial obliga a escribir la accion y el responsable: sin eso la fila no esta diligenciada. La hoja Resumen cuenta automaticamente y no hay que tocarla.
A10: Regla que hace util la lista
A11: Un criterio solo se marca como cumplido cuando alguien lo comprobó sobre la aplicación en marcha y puede decir cómo. Marcarlo porque «debería funcionar» convierte la lista en un trámite y deja los problemas para el día de la sustentación.
A13: Hojas del instrumento
A14: Hoja | B14: Que verifica | C14: Criterios | D14: Responsable
A15: Chequeo_Documental | B15: Los 10 criterios de cierre que exige el marco documental del programa (GOB-01, seccion 12). | C15: 10 | D15: Harryson [apellidos por completar]
A16: Chequeo_Producto | B16: Que cada modulo funcione de punta a punta, con la aplicacion en marcha. | C16: 34 | D16: Harryson, Jessica y Dayana
A17: Chequeo_Tecnico | B17: Codigo, pruebas, integracion continua, seguridad, datos y despliegue. | C17: 30 | D17: Harryson [apellidos por completar]
A18: Chequeo_Sustentacion | B18: Que el equipo pueda demostrar y explicar lo entregado. | C18: 16 | D18: Harryson, Jessica y Dayana
A19: Nivel_de_Madurez | B19: Autoevaluacion contra la escala de 0 a 4 del marco documental. | C19: 5 | D19: Harryson [apellidos por completar]
A20: Resumen | B20: Conteo automatico y decision de entrega. No se edita. | C20: - | D20: Automatico
A23: Fechas
A24: Congelamiento de codigo: 18 de septiembre de 2026. Entrega y sustentacion: 20 de septiembre de 2026. Esta lista se diligencia completa al menos cinco dias antes del congelamiento, para que quede margen de correccion.
A26: Version 1.1 | 13 de septiembre de 2026 | Elaboro: Harryson [apellidos por completar] | Reviso: Jessica [apellidos por completar] | Instructor: Juan Carlos Quintero Romero

Sheet Chequeo_Documental
A1: CRITERIOS DE CIERRE DEL PROYECTO — SIGTM
A3: N. | B3: Criterio | C3: Cumple | D3: Evidencia que lo respalda | E3: Accion si no cumple | F3: Responsable
A4: 1 | B4: Cada información tiene una sola fuente de verdad. | C4: Si | D4: Los quince entregables salen de un mismo catálogo de requisitos y reglas. | E4: — | F4: Harryson
A5: 2 | B5: Los documentos comparten códigos, versiones y convenciones. | C5: Si | D5: Los quince usan la misma numeración ADSO y la versión 1.5. | E5: — | F5: Harryson
A6: 3 | B6: Existe trazabilidad desde el problema hasta la evidencia. | C6: Si | D6: La matriz traza 67 requisitos funcionales y 18 no funcionales. | E6: — | F6: Harryson
A7: 4 | B7: Los requisitos de calidad tienen métrica y método de verificación. | C7: Si | D7: Los 18 requisitos no funcionales del documento de alcance los declaran. | E7: — | F7: Harryson
A8: 5 | B8: Las reglas de negocio están centralizadas en un solo documento. | C8: Si | D8: Las 30 reglas están en el alcance y los demás documentos las citan por código. | E8: — | F8: Harryson
A9: 6 | B9: Los artefactos técnicos están documentados. | C9: Parcial | D9: Diez decisiones arquitectónicas registradas; faltan exportar los diagramas. | E9: Exportar los cinco diagramas a /docs/arquitectura | F9: Harryson, 16/09/2026
A10: 7 | B10: La documentación coincide con lo que hay en el repositorio. | C10: Parcial | D10: El código verificado coincide; falta resolver el permiso de escritura para subirlo todo. | E10: Resolver el permiso de colaborador | F10: Harryson, 13/09/2026
A11: 8 | B11: Los elementos condicionales están justificados. | C11: Si | D11: Las siete exclusiones del alcance están declaradas con su motivo. | E11: — | F11: Harryson
A12: 9 | B12: La documentación declara lo que no cumple. | C12: Si | D12: Cobertura de pruebas en cero, hallazgo de accesibilidad y prueba de usabilidad sin ejecutar. | E12: — | F12: Harryson
A13: 10 | B13: El equipo puede explicar cualquier parte del proyecto. | C13: Parcial | D13: Harryson domina servidor y datos; Jessica y Dayana, la interfaz. | E13: Ensayo cruzado antes de la sustentación | F13: Equipo, 17/09/2026
A14: 11 | B14: Las capturas del manual de usuario están tomadas. | C14: No | D14: El manual está escrito con instrucciones de qué capturar en cada punto. | E14: Tomar las trece capturas | F14: Dayana, 16/09/2026
A15: Estado al 11/09/2026: 7 criterios cumplen, 2 estan parciales y 1 no cumple. El unico que no cumple (N.7) depende de una sola accion: incorporar las tres ramas pendientes. Es la tarea de mayor prioridad del proyecto porque bloquea la correspondencia entre lo documentado y lo entregado, que es un criterio de cierre.

Sheet Chequeo_Producto
A1: VERIFICACIÓN FUNCIONAL — SIGTM
A3: N. | B3: Modulo | C3: Que se verifica | D3: RF | E3: Cumple | F3: Como se comprueba | G3: Observacion | H3: Responsable
A4: 1 | B4: Identidad | C4: Una persona puede crear su cuenta como cliente. | D4: RF-001 | E4: Si | F4: Registro desde UI-001. | H4: Jessica
A5: 2 | B5: Identidad | C5: El registro no permite crear cuentas con rol elevado. | D5: RF-001 | E5: Si | F5: Petición con rol ADMINISTRADOR: rechazada. | G5: Cerró el hallazgo SEG-01. | H5: Harryson
A6: 3 | B6: Identidad | C6: Los cuatro roles inician sesión y llegan a su pantalla. | D6: RF-002 | E6: Si | F6: Entrada con las cinco cuentas de la semilla. | H6: Jessica
A7: 4 | B7: Identidad | C7: Una cuenta desactivada no puede entrar. | D7: RF-002 | E7: Si | F7: Desactivar y volver a intentar. | H7: Harryson
A8: 5 | B8: Identidad | C8: Se puede recuperar y restablecer la contraseña. | D8: RF-005, RF-006 | E8: Si | F8: Recorrido completo: pedir enlace, abrirlo y entrar con la clave nueva. | G8: Construido el 13/09. Enlace de un solo uso, caduca en 30 min. Verificado con pruebas/integracion/recuperacion.js: 15 comprobaciones. | H8: Harryson, 13/09/2026
A9: 6 | B9: Identidad | C9: Al cambiar la contraseña se cierran las sesiones abiertas. | D9: RF-009 | E9: Si | F9: Usar el token anterior tras restablecer. | G9: Cerró el hallazgo SEG-04. | H9: Harryson
A10: 7 | B10: Identidad | C10: La verificación anti-automatización se ejerce. | D10: RF-003 | E10: Si | F10: Entrar sin resolver el desafio: el boton queda inactivo. | G10: Cerro el hallazgo SEG-08. El formulario envia el token real de Google. | H10: Harryson, 13/09/2026
A11: 8 | B11: Usuarios | C11: El administrador crea cuentas de personal. | D11: RF-012 | E11: Si | F11: Alta de un mecánico desde UI-014. | H11: Jessica
A12: 9 | B12: Usuarios | C12: No se puede desactivar el último administrador. | D12: RF-014 | E12: Si | F12: Intento dirigido con un solo administrador activo. | H12: Harryson
A13: 10 | B13: Usuarios | C13: Un administrador no puede desactivarse a sí mismo. | D13: RF-014 | E13: Si | F13: Intento dirigido. | H13: Harryson
A14: 11 | B14: Clientes | C14: Se registra un cliente y se le crea su cuenta. | D14: RF-015 | E14: Si | F14: Alta desde UI-009. | H14: Jessica
A15: 12 | B15: Motocicletas | C15: No se admiten dos motocicletas con la misma placa. | D15: RF-020 | E15: Si | F15: Alta con placa repetida: rechazada. | H15: Jessica
A16: 13 | B16: Citas | C16: Se agenda, confirma y completa una cita. | D16: RF-026, RF-030 | E16: Si | F16: Recorrido en UI-011. | H16: Jessica
A17: 14 | B17: Órdenes | C17: Al abrir una orden se genera su código público. | D17: RF-033 | E17: Si | F17: Alta desde UI-008; código con formato OT-AAAA-XXXXXX. | H17: Jessica
A18: 15 | B18: Órdenes | C18: No se abre una orden con moto de otro cliente. | D18: RF-033 | E18: Si | F18: Intento dirigido. | H18: Harryson
A19: 16 | B19: Órdenes | C19: Solo se asigna como mecánico a quien tiene ese rol. | D19: RF-038 | E19: Si | F19: Intento con una recepcionista: rechazado. | H19: Harryson
A20: 17 | B20: Órdenes | C20: Una transición inválida se rechaza con mensaje claro. | D20: RF-039 | E20: Si | F20: Intento de pasar de RECIBIDA a ENTREGADA. | G20: El mensaje enumera las válidas. | H20: Harryson
A21: 18 | B21: Órdenes | C21: Una orden entregada no admite más cambios. | D21: RF-039 | E21: Si | F21: Intento dirigido. | H21: Harryson
A22: 19 | B22: Auditoría | C22: Cada cambio de estado deja autor, fecha y estado anterior. | D22: RF-061 | E22: Si | F22: Inspección del historial tras avanzar una orden. | H22: Harryson
A23: 20 | B23: Auditoría | C23: No existe cambio de estado sin su asiento. | D23: RF-061 | E23: Si | F23: Ambas escrituras en la misma transacción. | H23: Harryson
A24: 21 | B24: Diagnóstico | C24: El mecánico registra diagnóstico y mano de obra. | D24: RF-045 | E24: Si | F24: Recorrido con mecanico1@sigtm.com. | H24: Jessica
A25: 22 | B25: Diagnóstico | C25: El total suma mano de obra e ítems por su cantidad. | D25: RF-050 | E25: Si | F25: Cotización con valores conocidos. | H25: Harryson
A26: 23 | B26: Inventario | C26: No se admiten dos repuestos con el mismo código. | D26: RF-051 | E26: Si | F26: Alta con código repetido: rechazada. | H26: Jessica
A27: 24 | B27: Inventario | C27: Los repuestos bajo mínimo aparecen en el aviso. | D27: RF-053 | E27: Si | F27: La semilla deja dos por debajo a propósito. | H27: Jessica
A28: 25 | B28: Inventario | C28: El inventario se descuenta al terminar la reparación. | D28: RF-056 | E28: No | F28: Completar una orden y revisar existencias. | G28: Deuda DT-04: la salida se registra a mano. | H28: —
A29: 26 | B29: Facturación | C29: Se genera la factura con número único. | D29: RF-058 | E29: Si | F29: Emisión desde UI-007. | H29: Jessica
A30: 27 | B30: Portal | C30: El cliente ve sus motos, citas y órdenes. | D30: RF-036 | E30: Si | F30: Entrada con cliente@sigtm.com. | H30: Dayana
A31: 28 | B31: Portal | C31: El cliente ve la línea de tiempo de cinco pasos. | D31: RF-044 | E31: Si | F31: Portal del cliente con una orden avanzada. | H31: Dayana
A32: 29 | B32: Portal | C32: Un cliente no puede ver datos de otro. | D32: RF-035 | E32: Si | F32: Alterar el identificador en la dirección: 403. | G32: Cerró el hallazgo SEG-02. | H32: Harryson
A33: 30 | B33: Seguimiento | C33: La consulta por código funciona sin sesión. | D33: RF-042 | E33: Si | F33: Ventana de incógnito con un código válido. | H33: Dayana
A34: 31 | B34: Seguimiento | C34: La consulta pública no expone datos personales ni precios. | D34: RF-043 | E34: Si | F34: Inspección del cuerpo de la respuesta. | G34: Cerró el hallazgo SEG-03. | H34: Harryson
A35: 32 | B35: Seguimiento | C35: Un código inexistente responde sin revelar nada. | D35: RF-042 | E35: Si | F35: Consulta con código inventado. | H35: Dayana
A36: 33 | B36: Notificaciones | C36: El cliente recibe aviso al cambiar de etapa. | D36: RF-063 | E36: Parcial | F36: Avanzar una orden a LISTA y revisar el buzon. | G36: El aviso se dispara y se verifico con pruebas/integracion/avisoCambioEstado.js (12 comprobaciones). Sin SMTP_HOST el correo va a una bandeja de prueba y no llega al destinatario: queda Parcial hasta configurar el proveedor. | H36: Harryson, 13/09/2026
A37: 34 | B37: Panel | C37: El panel muestra órdenes por estado y repuestos bajo mínimo. | D37: RF-067 | E37: Si | F37: Entrada con admin@sigtm.com. | H37: Jessica
A38: Estado al 13/09/2026: 32 de 34 verificaciones cumplen y 1 queda parcial. La recuperacion de contrasena y el captcha pasaron a cumplir el 13/09. El aviso por correo funciona pero no llega al destinatario hasta configurar el proveedor. El descuento automatico de inventario sigue sin hacerse: es la deuda DT-04, declarada.

Sheet Chequeo_Tecnico
A1: VERIFICACIÓN TÉCNICA — SIGTM
A3: N. | B3: Area | C3: Criterio | D3: Cumple | E3: Evidencia verificable | F3: Observacion
A4: 1 | B4: Arranque | C4: El servidor arranca sin errores. | D4: Si | E4: npm run dev en la raíz del proyecto.
A5: 2 | B5: Arranque | C5: El cliente compila y arranca. | D5: Si | E5: npm run dev dentro de frontend.
A6: 3 | B6: Arranque | C6: La aplicación no arranca si falta una variable obligatoria. | D6: Si | E6: Quitar DATABASE_URL y arrancar: sale con mensaje explícito. | F6: Es deliberado.
A7: 4 | B7: Contenedores | C7: El proyecto se levanta con un solo comando. | D7: Parcial | E7: docker compose up. | F7: Dockerfile, frontend/Dockerfile y docker-compose.yml escritos el 13/09 y validados con 'docker compose config'. Falta ejecutarlos: el equipo no tenia Docker Desktop en marcha.
A8: 5 | B8: Pruebas | C8: Existe una suite automatizada. | D8: Si | E8: npm test: 32 pruebas, 32 en verde, sin base de datos. | F8: Cerro la deuda DT-07. Cubre la maquina de estados, los tokens de seguridad, el limite de intentos y la regla de cuando se avisa al cliente.
A9: 6 | B9: Integración continua | C9: Cada envío dispara análisis y pruebas. | D9: Si | E9: .github/workflows/ci.yml. | F9: Cerro la deuda DT-08. Cada envio ejecuta pruebas, valida el esquema, compila el cliente y comprueba que no haya ningun .env versionado.
A10: 7 | B10: Base de datos | C10: El esquema se reconstruye desde cero con las migraciones. | D10: Si | E10: npx prisma migrate status y migrate diff. | F10: Tres migraciones. Se aplicaron las dos que faltaban con 'migrate deploy', sin reset y sin perder datos. Sin deriva contra el esquema.
A11: 8 | B11: Base de datos | C11: La semilla se puede ejecutar varias veces sin duplicar. | D11: Si | E11: npm run db:seed dos veces seguidas.
A12: 9 | B12: Base de datos | C12: Los importes conservan dos decimales exactos. | D12: Si | E12: Inspección del tipo decimal en el esquema.
A13: 10 | B13: Seguridad | C13: Las contraseñas se guardan cifradas. | D13: Si | E13: Inspección de la tabla de usuarios.
A14: 11 | B14: Seguridad | C14: Los tokens de correo se guardan cifrados. | D14: Si | E14: Inspeccion de la tabla tokens_seguridad. | F14: Se guarda la huella SHA-256, nunca el token. Del hash no se vuelve al enlace.
A15: 12 | B15: Seguridad | C15: El origen del navegador está declarado explícitamente. | D15: Si | E15: Petición desde un origen distinto: rechazada.
A16: 13 | B16: Seguridad | C16: Toda entrada se valida antes de la lógica de negocio. | D16: Si | E16: Validadores declarados en los endpoints con cuerpo o parámetros.
A17: 14 | B17: Seguridad | C17: Hay límite de intentos en las rutas sensibles. | D17: Si | E17: Seis solicitudes seguidas de recuperacion: la sexta responde 429. | F17: Registro, inicio de sesion, envio de correo, comprobacion de enlace y restablecimiento, cada uno con su propio contador.
A18: 15 | B18: Seguridad | C18: Hay cabeceras de seguridad configuradas. | D18: Si | E18: Inspeccion de las cabeceras de respuesta. | F18: helmet activo: X-Content-Type-Options, Referrer-Policy, X-Frame-Options y Strict-Transport-Security. Cerro la mitad de la deuda DT-02.
A19: 16 | B19: Seguridad | C19: Ningún secreto aparece en el repositorio. | D19: Si | E19: git check-ignore .env e inspección del historial.
A20: 17 | B20: Operación | C20: El chequeo de salud detecta la caída de la base de datos. | D20: Si | E20: GET /api/health con la base desconectada: responde 503.
A21: 18 | B21: Operación | C21: El servidor cierra de forma ordenada. | D21: Si | E21: Señal de término: cierra la conexión y sale.
A22: 19 | B22: Operación | C22: Los errores no exponen trazas internas al cliente. | D22: Si | E22: Provocar un error y revisar la respuesta.
A23: 20 | B23: Código | C23: Las capas respetan su dirección de dependencia. | D23: Si | E23: Solo los repositorios acceden al ORM.
A24: 21 | B24: Código | C24: Los finales de línea están normalizados entre equipos. | D24: Si | E24: Archivo .gitattributes en la raíz.
A25: 22 | B25: Documentación | C25: La API está catalogada con su permiso por endpoint. | D25: Si | E25: 61 endpoints en el documento de arquitectura.
A26: 23 | B26: Documentación | C26: La API está publicada en formato navegable. | D26: No | E26: No hay Swagger configurado. | F26: Deuda DT-10.
A27: Estado al 13/09/2026: 21 de 23 criterios cumplen y 1 queda parcial. Pruebas automatizadas, integracion continua y cabeceras de seguridad pasaron a cumplir el 13/09. Queda sin cumplir la publicacion navegable de la API (deuda DT-10).

Sheet Chequeo_Sustentacion
A1: PREPARACION DE LA SUSTENTACION
A3: N. | B3: Aspecto | C3: Criterio | D3: Listo | E3: Como se comprueba | F3: Responsable
A4: 1 | B4: Ambiente | C4: La aplicacion arranca en el equipo con el que se va a sustentar. | D4: Si | E4: Ensayo completo: imagen, contenedor, cliente y navegador. | F4: Harryson, Jessica y Dayana
A5: 2 | B5: Ambiente | C5: Hay datos de demostracion cargados y coherentes. | D5: No | E5: Un usuario con al menos dos meses de movimientos, presupuestos, una obligacion con pagos y una meta con abonos. | F5: Jessica [apellidos por completar], 05/09/2026
A6: 3 | B6: Ambiente | C6: Existe un usuario administrador para demostrar ese perfil. | D6: No | E6: Cuenta con rol de administrador y acciones registradas en la bitacora. | F6: Harryson, 05/09/2026
A7: 4 | B7: Ambiente | C7: Hay plan B si falla la conexion a internet. | D7: No | E7: docker compose up levanta PostgreSQL local. Ensayarlo con el cable desconectado. | F7: Harryson, 05/09/2026
A8: 5 | B8: Ambiente | C8: Hay respaldo del recorrido en video o capturas. | D8: No | E8: Grabacion del recorrido completo, por si el ambiente falla en vivo. | F8: Jessica [apellidos por completar], 18/09/2026
A9: 6 | B9: Guion | C9: El recorrido de la demostracion esta escrito y ensayado. | D9: No | E9: EVA-03, seccion del guion. Al menos dos ensayos cronometrados. | F9: Harryson, Jessica y Dayana, 18/09/2026
A10: 7 | B10: Guion | C10: El reparto entre los dos integrantes esta definido. | D10: No | E10: EVA-03. Quien habla en cada bloque y quien opera el equipo. | F10: Harryson, Jessica y Dayana, 18/09/2026
A11: 8 | B11: Guion | C11: La demostracion cabe en el tiempo asignado. | D11: No | E11: Cronometrar. Si sobra material, decidir antes que se recorta. | F11: Harryson, Jessica y Dayana, 18/09/2026
A12: 9 | B12: Dominio | C12: Cada integrante puede explicar el area del otro. | D12: No | E12: Ensayo cruzado: Jessica [apellidos por completar] explica la descomposicion de intereses, Harryson explica la navegacion del cliente. | F12: Harryson, Jessica y Dayana, 05/09/2026
A13: 10 | B13: Dominio | C13: El equipo puede justificar las decisiones de arquitectura. | D13: Parcial | E13: Los 17 ADR estan escritos en ARQ-01. Harryson los domina; Jessica [apellidos por completar] no los ha repasado. | F13: Jessica [apellidos por completar], 05/09/2026
A14: 11 | B14: Dominio | C14: El equipo puede explicar por que las tarjetas no suman al disponible. | D14: Si | E14: RN-020 y DEF-01. Es la anecdota mas util del proyecto: el defecto lo encontro el equipo usando la aplicacion. | F14: Harryson, Jessica y Dayana
A15: 12 | B15: Dominio | C15: El equipo puede responder por los defectos y por lo que cambio cada uno. | D15: Si | E15: CAL-01 documenta 12 defectos con causa raiz y cambio de proceso. | F15: Harryson
... A19: 16 | B19: Entrega | C19: El repositorio esta accesible para el instructor. | D19: Si | E19: Repositorio con acceso concedido. Enlace en el Indice Maestro. | F19: Harryson
A21: Esta es la hoja mas roja del instrumento, y es lo esperado el 11 de septiembre: la preparacion de la sustentacion se hace al final. Lo que importa es que las 9 casillas en No tienen responsable y fecha, todas anteriores al congelamiento de codigo del 8 de septiembre. Una casilla en No con fecha es una tarea; sin fecha es una sorpresa.

Sheet Nivel_de_Madurez
A1: AUTOEVALUACION DE MADUREZ · escala de GOB-01, seccion 11
A3: Nivel | B3: Estado | C3: Documentacion esperada | D3: Alcanzado | E3: Evidencia en SIGTM | F3: Lo que faltaria
A4: 0 | B4: No demostrable | C4: Producto no ejecutable o documentacion sin correspondencia. | D4: Superado | E4: La aplicacion se ejecuta y los documentos corresponden a lo construido. | F4: -
A5: 1 | B5: Prototipo basico | C5: Formulacion, alcance, backlog y diseno basico. | D5: Superado | E5: INI-01, GES-01, REQ-01, REQ-02 y DSN-01 completos. 20 pantallas disenadas. | F5: -
A6: 2 | B6: Producto funcional | C6: Documentos principales minimos, pruebas criticas, despliegue reproducible. | D6: Alcanzado | E6: Trece modulos funcionales, 61 endpoints con permiso verificado, doce entidades, tres migraciones versionadas, base administrada en Neon y empaquetado en contenedores escrito y validado. | F6: -
A7: 3 | B7: Producto profesional | C7: Seguridad, pruebas, integracion continua, manuales, operacion y trazabilidad solidas. | D7: Alcanzado con una salvedad | E7: Seguridad con los ocho hallazgos cerrados y propiedad del recurso comprobada en el servidor; 32 pruebas de unidad y 27 comprobaciones de integracion; integracion continua en cada envio; manuales tecnico y de usuario; matriz de trazabilidad de 85 filas sin huecos. | F7: Falta ejecutar el empaquetado en contenedores y configurar el proveedor de correo, y falta la etiqueta de version que ligue lo entregado con lo documentado.
A8: 4 | B8: Producto avanzado | C8: Observabilidad, rendimiento, accesibilidad, automatizacion y escalabilidad verificadas. | D8: No alcanzado | E8: Hay accesibilidad verificada por medicion (contraste de los 10 pares del sistema de diseno) y automatizacion parcial (compilar y probar en cada peticion). | F8: Sin metricas de observabilidad mas alla del chequeo de disponibilidad, sin medicion de rendimiento bajo carga, sin despliegue automatico y sin separacion entre pruebas y produccion. Fuera del alcance academico.
A10: Autoevaluacion: nivel 3, producto profesional, con una salvedad concreta y con fecha. No se reclama nivel 4: falta observabilidad, medicion de rendimiento y separacion de ambientes, y reclamarlo seria facil de desmontar en la sustentacion con una sola pregunta. Declarar el nivel real y saber exactamente que falta para el siguiente vale mas que reclamar uno de mas.

Sheet Resumen
A1: RESUMEN Y DECISION DE ENTREGA · hoja calculada, no se edita
A3: Hoja | B3: Criterios | C3: Cumple | D3: No cumple | E3: Parcial | F3: N.A. | G3: % de avance
A4: Chequeo_Documental | B4: =COUNTA(Chequeo_Documental!C4:C13) | C4: =COUNTIF(Chequeo_Documental!C4:C13,"Si") | D4: =COUNTIF(Chequeo_Documental!C4:C13,"No") | E4: =COUNTIF(Chequeo_Documental!C4:C13,"Parcial") | F4: =COUNTIF(Chequeo_Documental!C4:C13,"N.A.") | G4: =IF(B4=0,0,C4/B4)
A5: Chequeo_Producto | B5: =COUNTA(Chequeo_Producto!E4:E37) | C5: =COUNTIF(Chequeo_Producto!E4:E37,"Si") | D5: =COUNTIF(Chequeo_Producto!E4:E37,"No") | E5: =COUNTIF(Chequeo_Producto!E4:E37,"Parcial") | F5: =COUNTIF(Chequeo_Producto!E4:E37,"N.A.") | G5: =IF(B5=0,0,C5/B5)
A6: Chequeo_Tecnico | B6: =COUNTA(Chequeo_Tecnico!D4:D33) | C6: =COUNTIF(Chequeo_Tecnico!D4:D33,"Si") | D6: =COUNTIF(Chequeo_Tecnico!D4:D33,"No") | E6: =COUNTIF(Chequeo_Tecnico!D4:D33,"Parcial") | F6: =COUNTIF(Chequeo_Tecnico!D4:D33,"N.A.") | G6: =IF(B6=0,0,C6/B6)
A7: Chequeo_Sustentacion | B7: =COUNTA(Chequeo_Sustentacion!D4:D19) | C7: =COUNTIF(Chequeo_Sustentacion!D4:D19,"Si") | D7: =COUNTIF(Chequeo_Sustentacion!D4:D19,"No") | E7: =COUNTIF(Chequeo_Sustentacion!D4:D19,"Parcial") | F7: =COUNTIF(Chequeo_Sustentacion!D4:D19,"N.A.") | G7: =IF(B7=0,0,C7/B7)
A8: TOTAL | B8: =SUM(B4:B7) | C8: =SUM(C4:C7) | D8: =SUM(D4:D7) | E8: =SUM(E4:E7) | F8: =SUM(F4:F7) | G8: =IF(B8=0,0,C8/B8)
A10: Regla de decision
A11: El proyecto se entrega cuando: (a) ningun criterio del Chequeo_Documental esta en No, porque son los criterios de cierre del programa; (b) el Chequeo_Tecnico no tiene ningun No; (c) el Chequeo_Producto no tiene ningun No en un modulo del alcance comprometido; y (d) el Chequeo_Sustentacion esta completo. Un Parcial es aceptable si tiene responsable y fecha anterior al congelamiento de codigo.
A13: Situacion al 11 de septiembre de 2026
A14: De 90 criterios, 74 cumplen, 3 estan parciales y 13 estan en No. Los 13 en No se reducen a tres asuntos, no a trece problemas distintos:
A15: 1. Las tres ramas pendientes de incorporar (2 criterios). Aparece en dos hojas porque tiene dos consecuencias: rompe la correspondencia entre lo documentado y lo entregado, y deja develop con un esquema anterior al de la base. Una sola accion cierra los dos criterios. Harryson, 22/08/2026.
A16: 2. Las claves de Google y del proveedor de captcha (2 criterios). Los dos flujos estan escritos y probados; lo que falta es generar credenciales en dos consolas externas, gratuitas y sin tarjeta. Es configuracion, no desarrollo. Harryson, 05/09/2026.
A17: 3. La preparacion de la sustentacion: datos de demostracion, guion, ensayos y plan B (9 criterios). Nueve casillas que por naturaleza se hacen al final. Harryson, Jessica y Dayana, 18/09/2026.
A19: Decision: el proyecto NO esta listo para entregar el 11 de septiembre, y no tenia por que estarlo. Esta listo para entregar cuando los tres asuntos anteriores se cierren, todos con fecha anterior al congelamiento de codigo del 8 de septiembre. La utilidad de esta lista es precisamente esa: encontrar los trece ahora y no descubrirlos el 20 de septiembre.
A21: Firmas
A22: Rol | B22: Nombre | C22: Fecha | D22: Decision
A23: Lider del proyecto | B23: Harryson Andres [apellidos por completar] | D23: Diligenciada
A24: Integrante | B24: Jessica [apellidos por completar] | D24: Revisada
A25: Instructor | B25: Juan Carlos Quintero Romero | D25: Aprobada / Devuelta
